LICENSE
MANIFEST.in
README.rst
setup.py
django_uikit_admin.egg-info/PKG-INFO
django_uikit_admin.egg-info/SOURCES.txt
django_uikit_admin.egg-info/dependency_links.txt
django_uikit_admin.egg-info/top_level.txt
uikit_admin/__init__.py
uikit_admin/admin.py
uikit_admin/models.py
uikit_admin/tests.py
uikit_admin/views.py
uikit_admin/static/admin/css/base.css
uikit_admin/static/admin/css/changelists.css
uikit_admin/static/admin/css/dashboard.css
uikit_admin/static/admin/css/forms.css
uikit_admin/static/admin/css/ie.css
uikit_admin/static/admin/css/index.css
uikit_admin/static/admin/css/login.css
uikit_admin/static/admin/css/rtl.css
uikit_admin/static/admin/css/widgets.css
uikit_admin/static/admin/img/changelist-bg.gif
uikit_admin/static/admin/img/changelist-bg_rtl.gif
uikit_admin/static/admin/img/default-bg-reverse.gif
uikit_admin/static/admin/img/default-bg.gif
uikit_admin/static/admin/img/deleted-overlay.gif
uikit_admin/static/admin/img/icon-no.gif
uikit_admin/static/admin/img/icon-unknown.gif
uikit_admin/static/admin/img/icon-yes.gif
uikit_admin/static/admin/img/icon_addlink.gif
uikit_admin/static/admin/img/icon_alert.gif
uikit_admin/static/admin/img/icon_calendar.gif
uikit_admin/static/admin/img/icon_changelink.gif
uikit_admin/static/admin/img/icon_clock.gif
uikit_admin/static/admin/img/icon_deletelink.gif
uikit_admin/static/admin/img/icon_error.gif
uikit_admin/static/admin/img/icon_searchbox.png
uikit_admin/static/admin/img/icon_success.gif
uikit_admin/static/admin/img/inline-delete-8bit.png
uikit_admin/static/admin/img/inline-delete.png
uikit_admin/static/admin/img/inline-restore-8bit.png
uikit_admin/static/admin/img/inline-restore.png
uikit_admin/static/admin/img/inline-splitter-bg.gif
uikit_admin/static/admin/img/nav-bg-grabber.gif
uikit_admin/static/admin/img/nav-bg-reverse.gif
uikit_admin/static/admin/img/nav-bg-selected.gif
uikit_admin/static/admin/img/nav-bg.gif
uikit_admin/static/admin/img/selector-icons.gif
uikit_admin/static/admin/img/selector-search.gif
uikit_admin/static/admin/img/sorting-icons.gif
uikit_admin/static/admin/img/tooltag-add.png
uikit_admin/static/admin/img/tooltag-arrowright.png
