Metadata-Version: 1.1
Name: django-uikit-admin
Version: 0.1
Summary: A modern grid based skin for Django built-in administration interface.
Home-page: https://github.com/epi-log/django-uikit-admin
Author: Nathan Bigaignon, Max Prudhomme
Author-email: nathanbigaignon@gmail.com
License: BSD License
Platform: UNKNOWN
Classifier: Environment :: Web Environment
Classifier: Framework :: Django
Classifier: Framework :: Django :: 1.8
Classifier: Intended Audience :: Developers
Classifier: License :: OSI Approved :: BSD License
Classifier: Operating System :: OS Independent
Classifier: Programming Language :: Python
Classifier: Programming Language :: Python :: 3
Classifier: Programming Language :: Python :: 3.4
Classifier: Programming Language :: Python :: 3.5
Classifier: Topic :: Internet :: WWW/HTTP
Classifier: Topic :: Internet :: WWW/HTTP :: Dynamic Content
